googlegeocoder/__init__.py
python_googlegeocoder-0.5.3.dist-info/LICENSE
python_googlegeocoder-0.5.3.dist-info/METADATA
python_googlegeocoder-0.5.3.dist-info/WHEEL
python_googlegeocoder-0.5.3.dist-info/top_level.txt
python_googlegeocoder-0.5.3.dist-info/RECORD
