Metadata-Version: 2.1
Name: python-googlegeocoder
Version: 0.5.3
Summary: A simple Python wrapper for Google’s geocoder API
Home-page: http://palewi.re/docs/python-googlegeocoder
Author: Ben Welsh
Author-email: b@palewi.re
License: GPL
Project-URL: Documentation, http://palewi.re/docs/python-googlegeocoder
Project-URL: Source, https://github.com/palewire/python-googlegeocoder
Project-URL: Tracker, https://github.com/palewire/python-googlegeocoder/issues
Classifier: Development Status :: 5 - Production/Stable
Classifier: Programming Language :: Python
Classifier: Programming Language :: Python :: 3
Classifier: Programming Language :: Python :: 3.9
Classifier: Programming Language :: Python :: 3.10
Classifier: Programming Language :: Python :: 3.11
Classifier: License :: OSI Approved :: GNU General Public License v3 (GPLv3)
License-File: LICENSE
